{
  "0012d10a61d77a76": "Ticari ve konut talebini artırır (3x3)",
  "010d027a9055baf1": "Küçük ofis binası",
  "012b78191d3eef87": "Hız Treni",
  "03e108901c6d428d": "Yolcu ve yük istasyonu",
  "06cf637219c05461": "Açık hava kamp alanı",
  "083a18f928c6f1d0": "Bölgeyi kaldır",
  "0df552c71ceffdea": "Açık hava basketbol sahası",
  "11e592ce36623118": "Belediye Binası",
  "16e15fc06c6a007c": "Halka açık yüzme tesisi",
  "1d322b583a4b0247": "Ticari talebi artırır (3x3)",
  "1e5fcd19bdbca49e": "Doğa yürüyüşü parkuru girişi (3x3)",
  "1f30c00e03eeca50": "Yol",
  "22afa76a44fbcefd": "Go-Kart Pisti",
  "236b49842190cde3": "Yangınlarla mücadele et",
  "2455ea3bff6fcd33": "Güvenliği artır",
  "277949eda13391e5": "Ticari",
  "27b33d5e7ca06b25": "Stadyum",
  "2a39b732be4c5afe": "Eğlence tesisi",
  "2e46736f6530763d": "Küçük Park",
  "315f62fadaa37351": "Sağlığı iyileştir (2x2)",
  "32957fce34b7e56b": "Arazi Şekillendirme",
  "361b52252c485db1": "Temel eğitim (2x2)",
  "3713fd8f06b7bdbd": "Yık",
  "37974ce5901faca4": "Açık hava gösteri alanı (2x2)",
  "38f4bf88be0f7fb8": "Park Kapısı",
  "3fed752c6b827eb4": "Kaykay parkı",
  "423be6bbfb254615": "Çevreyi iyileştirmek için ağaç dikin",
  "43f8d980f9a0671a": "Yeraltı ulaşımı",
  "441e4c507e4ad288": "Küçük Ofis",
  "4552acda39be69ce": "Bölgelendirmeyi kaldır",
  "459f0b9e4a127d63": "Su Kulesi",
  "46bcf1a804883ab0": "Ortak bahçe alanı",
  "482a95b964ba67dc": "Patika Başlangıcı",
  "482ea0cd55a6de89": "Topluluk Bahçesi",
  "4862ed8532afdefe": "Elektrik üret (2x2)",
  "4a55fb07d843e6b3": "Su Arazi Şekillendirme",
  "4abc7c18f4193dec": "Konut bölgesi",
  "4b6098b15618c700": "Metro",
  "4ca435219460c2ac": "Adrenalin eğlencesi (2x2)",
  "5151b5e97cd737af": "Toplum Merkezi",
  "51ba70d622cd0090": "Amfitiyatro",
  "5307628f223147b6": "Yerel topluluk merkezi",
  "5346721dd34606cc": "Elektrik Santrali",
  "5346848488eb3e6d": "Büyük Oyun Parkı",
  "56e589e66d790077": "Binaları ve bölgeleri kaldır",
  "5710fcf3d552b2e4": "İtfaiye Merkezi",
  "573173896178c5b2": "Lunapark",
  "5a08b8941a037d58": "Yerel beyzbol sahası (2x2)",
  "5bf5088caf591468": "Tribünlü spor sahası",
  "5e9e025cf3ae6fc7": "Büyük park (3x3)",
  "5ffa6e6366e41c69": "Yarış eğlencesi (2x2)",
  "6027a72931335033": "Fabrika bölgesi",
  "60eb6be4ae31cecb": "Daha fazla ekipmanlı büyük oyun alanı (2x2)",
  "62f43adf29906dd6": "Futbol Sahası",
  "668bac01a99df249": "Polis",
  "693839da902125cb": "İskele",
  "6bbf388c7005fa30": "Üniversite",
  "6e706fe5f4dead95": "Mağaza ve ofis bölgesi",
  "71ba7468560d8d94": "Küçük Oyun Parkı",
  "745eee8680d46de2": "Yüzme Havuzu",
  "7599ffe8c31a20dc": "Tenis Kortu",
  "7626b00fded50abc": "Ağaç",
  "786f78fa84e8f121": "Gölet manzaralı park",
  "7a2dd3bc72dfe4a0": "Futbol Sahası",
  "7db45eab1e6e4c9e": "Büyük Park",
  "830e21fdb11a5d4a": "Su sağla",
  "8422fd86fad87d61": "Metro ağına erişim",
  "84b3fc230d753c82": "Tren İstasyonu",
  "84bfc3db1e596cce": "Gölet Parkı",
  "884832efb61160d4": "Araziyi suya dönüştür",
  "8b5e8de8f4c85850": "Yükseköğretim (3x3)",
  "8e51a2f65e212afd": "Suyu karaya dönüştür",
  "907abc04009841aa": "Minyatür golf sahası (2x2)",
  "931f3cdc1db7ade0": "Çocuk hayvanat bahçesi / çiftlik hayvanları",
  "955389bd727d0995": "Futbol stadyumu (2x2)",
  "97513d561bf53e55": "Metro İstasyonu",
  "9963ed45f2043cb8": "Sera Bahçesi",
  "9d254026827d7830": "Tribünlü Saha",
  "9f624c646a344dd9": "Botanik sera (2x2)",
  "a7894306a08bac01": "Konut",
  "a7cc8ff7202beca4": "Rustik kır kaçamağı",
  "a916da3428403968": "Kaykay Parkı",
  "aa29c7e2f00fb24d": "Mutluluğu ve arsa değerini artırır (1x1)",
  "adb5a90c2189aa55": "Ticari ve endüstriyel talebi artırır (4x4)",
  "b3b7a1d6663ccd5f": "Hastane",
  "b453abc6c0aa9847": "Beyzbol Sahası",
  "b4619e9087ef77c7": "Uzay Programı",
  "b821113430f5f0af": "Demiryolu",
  "bad59346a21883a3": "Havalimanı",
  "bcfcdb828fb6febe": "Sanayi",
  "c1118dc21f1a3a70": "Futbol sahası",
  "c374929bd865ac52": "Doğa kaçamak kulübesi (2x2)",
  "c49fb569cf0344a1": "Şehrini bağla",
  "c56f5cbb6dbe8edb": "Kulübe",
  "c96a3fd1bbe8f38a": "Sanayi ve konut talebini artırır (3x3)",
  "cb91c05c442d6da0": "Sahil iskelesi (su kenarına yerleştirilmelidir)",
  "cba582095df8e4d9": "Mini Golf",
  "ce17b8c1c26494e0": "Kamp Alanı",
  "cf5babe756808083": "Marina",
  "d08f67cf675a3159": "Profesyonel beyzbol sahası (3x3)",
  "d26290781c575c73": "Müze",
  "d5120487d8637bd5": "Dekoratif park girişi",
  "d76336950671d1e2": "Tekne iskeleleri (2x2, suyun yanına yerleştirilmelidir)",
  "d8f8e96fe087aec3": "Beyzbol Stadyumu",
  "d960080f10b5a21e": "Tüm talep türlerini artırır (2x2)",
  "e0fa959d80ac0d81": "Seç",
  "e23439349cbca510": "Karo bilgisini görmek için tıkla",
  "eaa9e68396589c20": "Demiryolu rayları döşe",
  "edb23f2758bbe9f9": "Okul",
  "eeca902329b200e6": "Dağ Evi",
  "f037be5184516560": "Çocuk parkı",
  "f2faf4aaea86ae97": "Basketbol Sahaları",
  "f69724f1685d216d": "Hayvan Ağıl­ları",
  "fbed860a569bfb30": "Ticari talepte büyük artış (4x4)"
}